expectation_helper/__init__.py
expectation_helper/settings.ini
expectation_helper-0.0.3.dist-info/LICENSE.txt
expectation_helper-0.0.3.dist-info/METADATA
expectation_helper-0.0.3.dist-info/WHEEL
expectation_helper-0.0.3.dist-info/top_level.txt
expectation_helper-0.0.3.dist-info/RECORD
