Metadata-Version: 2.1
Name: expectation-helper
Version: 0.0.3
Summary: Helpers for working with Great Expectations
Home-page: https://github.com/kenjyco/expectation-helper
Download-URL: https://github.com/kenjyco/expectation-helper/tarball/v0.0.3
Author: Ken
Author-email: kenjyco@gmail.com
License: MIT
Keywords: data,expectation,great expectations,gx,cli,command-line,helper,kenjyco
Classifier: Development Status :: 3 - Alpha
Classifier: Environment :: Console
Classifier: Intended Audience :: Developers
Classifier: License :: OSI Approved :: MIT License
Classifier: Operating System :: MacOS :: MacOS X
Classifier: Operating System :: POSIX :: Linux
Classifier: Programming Language :: Python :: 3.7
Classifier: Programming Language :: Python
Classifier: Topic :: Software Development :: Libraries
Classifier: Topic :: Utilities
License-File: LICENSE.txt
Requires-Dist: bg-helper
Requires-Dist: click (>=6.0)
Requires-Dist: input-helper
Requires-Dist: settings-helper
